<annotation>
    <filename>20250811-141138.jpg</filename>
    <folder>person_detect_dataset</folder>
    <source>
        <database>person_detect_dataset</database>
        <annotation>custom</annotation>
        <image>custom</image>
    </source>
    <size>
        <width>1280</width>
        <height>720</height>
        <depth>3</depth>
    </size>
    <segmented>0</segmented>
    <object>
        <name>student</name>
        <pose>unspecified</pose>
        <truncated>0</truncated>
        <difficult>0</difficult>
        <bndbox>
            <xmin>190</xmin>
            <ymin>23</ymin>
            <xmax>394</xmax>
            <ymax>734</ymax>
        </bndbox>
    </object>
    <object>
        <name>student</name>
        <pose>unspecified</pose>
        <truncated>0</truncated>
        <difficult>0</difficult>
        <bndbox>
            <xmin>456</xmin>
            <ymin>18</ymin>
            <xmax>645</xmax>
            <ymax>727</ymax>
        </bndbox>
    </object>
    <object>
        <name>student</name>
        <pose>unspecified</pose>
        <truncated>0</truncated>
        <difficult>0</difficult>
        <bndbox>
            <xmin>765</xmin>
            <ymin>31</ymin>
            <xmax>962</xmax>
            <ymax>713</ymax>
        </bndbox>
    </object>
</annotation>
